clcat-0.0.3.data/purelib/clcat/__init__.py
clcat-0.0.3.data/purelib/clcat/ct_algos.so
clcat-0.0.3.data/purelib/clcat/libMDCTBone.so
clcat-0.0.3.data/purelib/clcat/libMDImaging.so
clcat-0.0.3.dist-info/DESCRIPTION.rst
clcat-0.0.3.dist-info/METADATA
clcat-0.0.3.dist-info/RECORD
clcat-0.0.3.dist-info/WHEEL
clcat-0.0.3.dist-info/metadata.json
clcat-0.0.3.dist-info/top_level.txt
