Metadata-Version: 2.0
Name: clcat
Version: 0.0.3
Summary: Clara Holoscan Clinical Algorithms Toolkit
Home-page: UNKNOWN
Author: NVIDIA Corporation
License: UNKNOWN
Platform: UNKNOWN
Requires-Python: >=3.8
Requires-Dist: patchelf
